{"Sts":[{"uid":"","name":"-","bduss_md5":"326064F6FCA35821E9855CB371D3A34A","total":0,"signed":0,"bq":0,"excep":0,"black":0,"wenku":"未签到","zhidao":"未签到","support":0,"head_url":"","is_valid":false,"sign_time":1621787012188,"timespan":0,"page_data":null},{"uid":"938949325","name":"o*袅","bduss_md5":"F7517ECB929143B23EFCBC856509BB41","total":7,"signed":7,"bq":0,"excep":0,"black":0,"wenku":"已签到","zhidao":"已签到","support":1,"head_url":"https://himg.baidu.com/sys/portrait/item/tb.1.7c3a20ee.9i52rWulWWnEB3oWmuAVMQ","is_valid":true,"sign_time":1621787018208,"timespan":4328,"page_data":[{"list":[{"name":"风雨大姨妈","avatar":"http://imgsrc.baidu.com/forum/pic/item/faedab64034f78f0de6d10fc77310a55b3191c5e.jpg","level_id":"13","cur_score":"15233","levelup_score":"18000","error_code":"0","ret_msg":"签到成功","sign_time":1621787014016},{"name":"剑网3","avatar":"http://imgsrc.baidu.com/forum/pic/item/9345d688d43f8794ff5e0941d31b0ef41bd53a3f.jpg","level_id":"13","cur_score":"15045","levelup_score":"18000","error_code":"0","ret_msg":"签到成功","sign_time":1621787014415},{"name":"暖暖环游世界","avatar":"http://imgsrc.baidu.com/forum/pic/item/aa18972bd40735fab618f7ce98510fb30e2408d8.jpg","level_id":"13","cur_score":"15048","levelup_score":"18000","error_code":"0","ret_msg":"签到成功","sign_time":1621787014065},{"name":"熹妃传","avatar":"http://imgsrc.baidu.com/forum/pic/item/5366d0160924ab18b54c60cb3cfae6cd7a890bf7.jpg","level_id":"13","cur_score":"14886","levelup_score":"18000","error_code":"0","ret_msg":"签到成功","sign_time":1621787014489},{"name":"多肉","avatar":"http://imgsrc.baidu.com/forum/pic/item/b90e7bec54e736d188d3610099504fc2d46269f2.jpg","level_id":"13","cur_score":"14899","levelup_score":"18000","error_code":"0","ret_msg":"签到成功","sign_time":1621787014501},{"name":"完美世界","avatar":"http://imgsrc.baidu.com/forum/pic/item/1cda374e251f95ca3344909fc7177f3e660952b2.jpg","level_id":"12","cur_score":"6775","levelup_score":"10000","error_code":"0","ret_msg":"签到成功","sign_time":1621787014752},{"name":"世界rpg","avatar":"http://imgsrc.baidu.com/forum/pic/item/5243fbf2b2119313653243ae62380cd791238dbf.jpg","level_id":"11","cur_score":"5315","levelup_score":"6000","error_code":"0","ret_msg":"签到成功","sign_time":1621787015089}],"page_no":1,"page_size":0,"pages":[1],"total_pages":1,"total":7,"first_page":1,"last_page":2}]},{"uid":"1465394","name":"西*秦","bduss_md5":"73FEFB075CFA6BACC3990473D8667239","total":127,"signed":126,"bq":1,"excep":0,"black":0,"wenku":"已签到","zhidao":"已签到","support":2,"head_url":"https://himg.baidu.com/sys/portrait/item/tb.1.7f566276.G5kdZV68udUiX4YP5d1Rmw","is_valid":true,"sign_time":1621787039222,"timespan":49150,"page_data":[{"list":[{"name":"剑网3","avatar":"http://imgsrc.baidu.com/forum/pic/item/9345d688d43f8794ff5e0941d31b0ef41bd53a3f.jpg","level_id":"14","cur_score":"21776","levelup_score":"30000","error_code":"160002","ret_msg":"亲，你之前已经签过了","sign_time":1621787015061},{"name":"成都东软学院","avatar":"http://imgsrc.baidu.com/forum/pic/item/267f9e2f07082838fbfdda5aba99a9014d08f188.jpg","level_id":"14","cur_score":"21623","levelup_score":"30000","error_code":"160002","ret_msg":"亲，你之前已经签过了","sign_time":1621787015122},{"name":"完美国际","avatar":"http://imgsrc.baidu.com/forum/pic/item/c82a59ed2e738bd41b7db018af8b87d6267ff9dd.jpg","level_id":"14","cur_score":"21617","levelup_score":"30000","error_code":"160002","ret_msg":"亲，你之前已经签过了","sign_time":1621787015404},{"name":"lol","avatar":"http://tiebapic.baidu.com/forum/pic/item/0dd7912397dda144219990eea5b7d0a20df486de.jpg","level_id":"14","cur_score":"21768","levelup_score":"30000","error_code":"160002","ret_msg":"亲，你之前已经签过了","sign_time":1621787015101},{"name":"ems","avatar":"http://tiebapic.baidu.com/forum/pic/item/c2cec3fdfc0392459411a0659094a4c27d1e2537.jpg","level_id":"14","cur_score":"21593","levelup_score":"30000","error_code":"160002","ret_msg":"亲，你之前已经签过了","sign_time":1621787015691},{"name":"ぷ幻风☆","avatar":"http://imgsrc.baidu.com/forum/pic/item/826f3b10b912c8fcacd52597f5039245d78821af.jpg","level_id":"14","cur_score":"21591","levelup_score":"30000","error_code":"160002","ret_msg":"亲，你之前已经签过了","sign_time":1621787015807},{"name":"笑傲江湖","avatar":"http://imgsrc.baidu.com/forum/pic/item/7aec54e736d12f2e0fd425b441c2d56284356815.jpg","level_id":"14","cur_score":"21585","levelup_score":"30000","error_code":"160002","ret_msg":"亲，你之前已经签过了","sign_time":1621787016013},{"name":"考古","avatar":"http://imgsrc.baidu.com/forum/pic/item/902397dda144ad34af01c462d1a20cf430ad859d.jpg","level_id":"14","cur_score":"21580","levelup_score":"30000","error_code":"160002","ret_msg":"亲，你之前已经签过了","sign_time":1621787016161},{"name":"小子love丫头","avatar":"http://imgsrc.baidu.com/forum/pic/item/4afbfbedab64034f02be8de1aec379310b551de1.jpg","level_id":"14","cur_score":"21578","levelup_score":"30000","error_code":"160002","ret_msg":"亲，你之前已经签过了","sign_time":1621787016299},{"name":"天下3","avatar":"http://imgsrc.baidu.com/forum/pic/item/e928b794a4c27d1e7fe7a16311d5ad6edcc4386f.jpg","level_id":"14","cur_score":"21577","levelup_score":"30000","error_code":"160002","ret_msg":"亲，你之前已经签过了","sign_time":1621787016418},{"name":"amd","avatar":"http://imgsrc.baidu.com/forum/pic/item/2f738bd4b31c870153a4a7b7267f9e2f0708ff55.jpg","level_id":"14","cur_score":"21605","levelup_score":"30000","error_code":"160002","ret_msg":"亲，你之前已经签过了","sign_time":1621787016419},{"name":"鲁迅","avatar":"http://imgsrc.baidu.com/forum/pic/item/7acb0a46f21fbe09894b94f26a600c338744ad3b.jpg","level_id":"14","cur_score":"21577","levelup_score":"30000","error_code":"160002","ret_msg":"亲，你之前已经签过了","sign_time":1621787016639},{"name":"魔兽玩家","avatar":"http://imgsrc.baidu.com/forum/pic/item/6a600c338744ebf8d1fb2fc7dbf9d72a6159a744.jpg","level_id":"14","cur_score":"21573","levelup_score":"30000","error_code":"160002","ret_msg":"亲，你之前已经签过了","sign_time":1621787016819},{"name":"truelaunchbar","avatar":"http://imgsrc.baidu.com/forum/pic/item/a8ec8a13632762d0a3a85de9acec08fa503dc6d6.jpg","level_id":"14","cur_score":"21565","levelup_score":"30000","error_code":"160002","ret_msg":"亲，你之前已经签过了","sign_time":1621787016901},{"name":"李煜","avatar":"http://imgsrc.baidu.com/forum/pic/item/267f9e2f0708283884fb94eeb999a9014d08f152.jpg","level_id":"14","cur_score":"21565","levelup_score":"30000","error_code":"160002","ret_msg":"亲，你之前已经签过了","sign_time":1621787017053}],"page_no":1,"page_size":0,"pages":[1,2,3,4,5],"total_pages":9,"total":127,"first_page":1,"last_page":2},{"list":[{"name":"y400","avatar":"http://imgsrc.baidu.com/forum/pic/item/d439b6003af33a87f4720acac75c10385243b5c6.jpg","level_id":"14","cur_score":"21564","levelup_score":"30000","error_code":"160002","ret_msg":"亲，你之前已经签过了","sign_time":1621787017068},{"name":"魔兽世界","avatar":"http://imgsrc.baidu.com/forum/pic/item/622762d0f703918fdc00adb25c3d269758eec4f1.jpg","level_id":"14","cur_score":"21563","levelup_score":"30000","error_code":"160002","ret_msg":"亲，你之前已经签过了","sign_time":1621787017221},{"name":"未解之谜","avatar":"http://imgsrc.baidu.com/forum/pic/item/7af40ad162d9f2d3057dd80da2ec8a136227cce0.jpg","level_id":"14","cur_score":"21558","levelup_score":"30000","error_code":"160002","ret_msg":"亲，你之前已经签过了","sign_time":1621787017437},{"name":"英雄联盟","avatar":"http://tiebapic.baidu.com/forum/wh=120,120/sign=b43154a18b82d158bbd751b0b23a35e9/c75c10385343fbf2d729746ca77eca8065388f7c.jpg","level_id":"14","cur_score":"21558","levelup_score":"30000","error_code":"160002","ret_msg":"亲，你之前已经签过了","sign_time":1621787017491},{"name":"凯尔特","avatar":"http://imgsrc.baidu.com/forum/pic/item/9345d688d43f8794c046169fd31b0ef41ad53ac1.jpg","level_id":"14","cur_score":"21555","levelup_score":"30000","error_code":"160002","ret_msg":"亲，你之前已经签过了","sign_time":1621787017672},{"name":"热血传奇","avatar":"http://imgsrc.baidu.com/forum/pic/item/241f95cad1c8a786c0d8cfbc6609c93d71cf5095.jpg","level_id":"14","cur_score":"21551","levelup_score":"30000","error_code":"160002","ret_msg":"亲，你之前已经签过了","sign_time":1621787017785},{"name":"联想y400","avatar":"http://imgsrc.baidu.com/forum/pic/item/826f3b10b912c8fcacd52597f5039245d78821af.jpg","level_id":"14","cur_score":"21546","levelup_score":"30000","error_code":"160002","ret_msg":"亲，你之前已经签过了","sign_time":1621787017840},{"name":"最终幻想","avatar":"http://imgsrc.baidu.com/forum/pic/item/b17eca8065380cd7a2eea25fa044ad345882818b.jpg","level_id":"14","cur_score":"21546","levelup_score":"30000","error_code":"160002","ret_msg":"亲，你之前已经签过了","sign_time":1621787018038},{"name":"刘德华","avatar":"http://tiebapic.baidu.com/forum/wh=120,120/sign=9b1e167d274e251fe2a2ecf995b6e526/b3b7d0a20cf431ad11c5f77e5c36acaf2edd9866.jpg","level_id":"14","cur_score":"21545","levelup_score":"30000","error_code":"160002","ret_msg":"亲，你之前已经签过了","sign_time":1621787018152},{"name":"海淘","avatar":"http://tb1.bdstatic.com/tb/r/image/2013-11-18/0dbb3d89d98c497ef6ef92486fd59d81.png","level_id":"14","cur_score":"21539","levelup_score":"30000","error_code":"160002","ret_msg":"亲，你之前已经签过了","sign_time":1621787018380},{"name":"陈乔恩","avatar":"http://imgsrc.baidu.com/forum/pic/item/4034970a304e251f3774d88bab86c9177e3e53c5.jpg","level_id":"14","cur_score":"21539","levelup_score":"30000","error_code":"160002","ret_msg":"亲，你之前已经签过了","sign_time":1621787018552},{"name":"我叫mtonline","avatar":"http://imgsrc.baidu.com/forum/pic/item/1ad5ad6eddc451da23521593bcfd5266d0163225.jpg","level_id":"14","cur_score":"21538","levelup_score":"30000","error_code":"160002","ret_msg":"亲，你之前已经签过了","sign_time":1621787018566},{"name":"系统集成项目管理工程师","avatar":"http://imgsrc.baidu.com/forum/pic/item/7c1ed21b0ef41bd518a7c94c5dda81cb38db3d95.jpg","level_id":"14","cur_score":"21537","levelup_score":"30000","error_code":"160002","ret_msg":"亲，你之前已经签过了","sign_time":1621787018722},{"name":"李商隐","avatar":"http://imgsrc.baidu.com/forum/pic/item/b219ebc4b74543a9c08778421b178a82b801149b.jpg","level_id":"14","cur_score":"21537","levelup_score":"30000","error_code":"160002","ret_msg":"亲，你之前已经签过了","sign_time":1621787018899},{"name":"科幻","avatar":"http://imgsrc.baidu.com/forum/pic/item/d000baa1cd11728bc2818747cbfcc3cec3fd2c22.jpg","level_id":"14","cur_score":"21529","levelup_score":"30000","error_code":"160002","ret_msg":"亲，你之前已经签过了","sign_time":1621787018958}],"page_no":2,"page_size":0,"pages":[1,2,3,4,5],"total_pages":9,"total":127,"first_page":1,"last_page":3},{"list":[{"name":"爆料","avatar":"http://imgsrc.baidu.com/forum/pic/item/5fdf8db1cb1349540a86455a534e9258d1094a77.jpg","level_id":"14","cur_score":"21524","levelup_score":"30000","error_code":"160002","ret_msg":"亲，你之前已经签过了","sign_time":1621787019144},{"name":"科幻电影","avatar":"http://imgsrc.baidu.com/forum/pic/item/15464b4a20a446238ddaa6809e22720e0df3d7a0.jpg","level_id":"14","cur_score":"21523","levelup_score":"30000","error_code":"160002","ret_msg":"亲，你之前已经签过了","sign_time":1621787019224},{"name":"成都","avatar":"http://imgsrc.baidu.com/forum/pic/item/1c950a7b02087bf4f4197d7af4d3572c10dfcfa8.jpg","level_id":"14","cur_score":"21523","levelup_score":"30000","error_code":"160002","ret_msg":"亲，你之前已经签过了","sign_time":1621787019356},{"name":"东盟","avatar":"http://imgsrc.baidu.com/forum/pic/item/203fb80e7bec54e77ed019f1bb389b504fc26a24.jpg","level_id":"14","cur_score":"21522","levelup_score":"30000","error_code":"160002","ret_msg":"亲，你之前已经签过了","sign_time":1621787019509},{"name":"windows8","avatar":"http://imgsrc.baidu.com/forum/pic/item/e850352ac65c10383b6814d0b8119313b07e898a.jpg","level_id":"14","cur_score":"21520","levelup_score":"30000","error_code":"160002","ret_msg":"亲，你之前已经签过了","sign_time":1621787019583},{"name":"唐家堡","avatar":"http://imgsrc.baidu.com/forum/pic/item/3b292df5e0fe9925157cb5bb33a85edf8cb171ed.jpg","level_id":"14","cur_score":"21506","levelup_score":"30000","error_code":"160002","ret_msg":"亲，你之前已经签过了","sign_time":1621787019818},{"name":"autohotkey","avatar":"http://imgsrc.baidu.com/forum/pic/item/48540923dd54564e105af1b0b2de9c82d1584f7f.jpg","level_id":"14","cur_score":"21505","levelup_score":"30000","error_code":"160002","ret_msg":"亲，你之前已经签过了","sign_time":1621787019823},{"name":"成龙","avatar":"http://imgsrc.baidu.com/forum/pic/item/72f082025aafa40f590d20f4af64034f79f019cb.jpg","level_id":"14","cur_score":"21505","levelup_score":"30000","error_code":"160002","ret_msg":"亲，你之前已经签过了","sign_time":1621787019954},{"name":"ufo","avatar":"http://imgsrc.baidu.com/forum/pic/item/d53f8794a4c27d1e465e32a219d5ad6eddc4385f.jpg","level_id":"14","cur_score":"21494","levelup_score":"30000","error_code":"160002","ret_msg":"亲，你之前已经签过了","sign_time":1621787020110},{"name":"风雨大姨妈","avatar":"http://imgsrc.baidu.com/forum/pic/item/faedab64034f78f0de6d10fc77310a55b3191c5e.jpg","level_id":"14","cur_score":"21471","levelup_score":"30000","error_code":"160002","ret_msg":"亲，你之前已经签过了","sign_time":1621787020410},{"name":"usps","avatar":"http://tiebapic.baidu.com/forum/wh=120,120/sign=477da68ab851f3dec3e7b165a6dedc2e/0d338744ebf81a4c8b648289c02a6059252da618.jpg","level_id":"14","cur_score":"21471","levelup_score":"30000","error_code":"160002","ret_msg":"亲，你之前已经签过了","sign_time":1621787020420},{"name":"诛仙","avatar":"http://imgsrc.baidu.com/forum/pic/item/21a4462309f790528caa682903f3d7ca7bcbd56b.jpg","level_id":"14","cur_score":"21418","levelup_score":"30000","error_code":"160002","ret_msg":"亲，你之前已经签过了","sign_time":1621787020596},{"name":"英雄战魂","avatar":"http://imgsrc.baidu.com/forum/pic/item/10dfa9ec8a136327eb445689908fa0ec09fac7db.jpg","level_id":"14","cur_score":"21408","levelup_score":"30000","error_code":"160002","ret_msg":"亲，你之前已经签过了","sign_time":1621787020716},{"name":"李毅","avatar":"http://imgsrc.baidu.com/forum/pic/item/aec379310a55b319380291c141a98226cefc178e.jpg","level_id":"14","cur_score":"21022","levelup_score":"30000","error_code":"160002","ret_msg":"亲，你之前已经签过了","sign_time":1621787021015},{"name":"剑三818","avatar":"http://imgsrc.baidu.com/forum/pic/item/9c16fdfaaf51f3de501e272c96eef01f3b2979ce.jpg","level_id":"14","cur_score":"21394","levelup_score":"30000","error_code":"160002","ret_msg":"亲，你之前已经签过了","sign_time":1621787021016}],"page_no":3,"page_size":0,"pages":[1,2,3,4,5],"total_pages":9,"total":127,"first_page":2,"last_page":4},{"list":[{"name":"淘米功夫派","avatar":"http://imgsrc.baidu.com/forum/pic/item/a9d3fd1f4134970af38ac1c29bcad1c8a6865d66.jpg","level_id":"14","cur_score":"20848","levelup_score":"30000","error_code":"160002","ret_msg":"亲，你之前已经签过了","sign_time":1621787021274},{"name":"节奏大师","avatar":"http://imgsrc.baidu.com/forum/pic/item/f603918fa0ec08fa8b8f75cc5aee3d6d54fbdaca.jpg","level_id":"14","cur_score":"20618","levelup_score":"30000","error_code":"160002","ret_msg":"亲，你之前已经签过了","sign_time":1621787021351},{"name":"天龙八部钟汉良版","avatar":"http://tb1.bdstatic.com/tb/cms/%E5%A4%A9%E9%BE%99%E5%85%AB%E9%83%A8%E5%A4%B4%E5%83%8F.jpg","level_id":"14","cur_score":"20406","levelup_score":"30000","error_code":"160002","ret_msg":"亲，你之前已经签过了","sign_time":1621787021621},{"name":"江津","avatar":"http://imgsrc.baidu.com/forum/pic/item/b3fb43166d224f4a2d746db108f790529922d1a6.jpg","level_id":"14","cur_score":"20462","levelup_score":"30000","error_code":"160002","ret_msg":"亲，你之前已经签过了","sign_time":1621787021660},{"name":"百度阅读","avatar":"http://imgsrc.baidu.com/forum/pic/item/8326cffc1e178a82069e738cfc03738da977e878.jpg","level_id":"13","cur_score":"15644","levelup_score":"18000","error_code":"160002","ret_msg":"亲，你之前已经签过了","sign_time":1621787021885},{"name":"梦幻西游手游","avatar":"http://imgsrc.baidu.com/forum/pic/item/22f87913632762d0e6ea16dfb7ec08fa503dc68b.jpg","level_id":"13","cur_score":"15309","levelup_score":"18000","error_code":"160002","ret_msg":"亲，你之前已经签过了","sign_time":1621787021958},{"name":"天猫魔盒","avatar":"http://imgsrc.baidu.com/forum/pic/item/96dda144ad34598278154ba705f431adcbef846c.jpg","level_id":"14","cur_score":"20375","levelup_score":"30000","error_code":"160002","ret_msg":"亲，你之前已经签过了","sign_time":1621787022210},{"name":"邀请码","avatar":"http://imgsrc.baidu.com/forum/pic/item/d8f9d72a6059252dfc150a0b339b033b5bb5b9ba.jpg","level_id":"14","cur_score":"20353","levelup_score":"30000","error_code":"160002","ret_msg":"亲，你之前已经签过了","sign_time":1621787022294},{"name":"传奇","avatar":"null","level_id":"14","cur_score":"20280","levelup_score":"30000","error_code":"160002","ret_msg":"亲，你之前已经签过了","sign_time":1621787022492},{"name":"技术宅","avatar":"http://imgsrc.baidu.com/forum/pic/item/f703738da97739126a1d9c0efb198618367ae2a2.jpg","level_id":"14","cur_score":"20198","levelup_score":"30000","error_code":"160002","ret_msg":"亲，你之前已经签过了","sign_time":1621787022550},{"name":"激战2","avatar":"http://tiebapic.baidu.com/forum/pic/item/0b55b319ebc4b7453807e977d8fc1e178a82153b.jpg","level_id":"14","cur_score":"19740","levelup_score":"30000","error_code":"160002","ret_msg":"亲，你之前已经签过了","sign_time":1621787022912},{"name":"iphone5s","avatar":"http://imgsrc.baidu.com/forum/pic/item/908fa0ec08fa513de40837123c6d55fbb3fbd958.jpg","level_id":"14","cur_score":"19562","levelup_score":"30000","error_code":"160002","ret_msg":"亲，你之前已经签过了","sign_time":1621787022915},{"name":"激战2国服","avatar":"http://imgsrc.baidu.com/forum/pic/item/30adcbef76094b36b13a7849a1cc7cd98c109ded.jpg","level_id":"14","cur_score":"19365","levelup_score":"30000","error_code":"160002","ret_msg":"亲，你之前已经签过了","sign_time":1621787023101},{"name":"firefox","avatar":"http://imgsrc.baidu.com/forum/pic/item/cdbf6c81800a19d86b057b6638fa828ba61e464b.jpg","level_id":"14","cur_score":"21476","levelup_score":"30000","error_code":"160002","ret_msg":"亲，你之前已经签过了","sign_time":1621787020186},{"name":"雨滴社区","avatar":"http://imgsrc.baidu.com/forum/pic/item/f7246b600c3387444e21befe500fd9f9d62aa048.jpg","level_id":"14","cur_score":"19288","levelup_score":"30000","error_code":"160002","ret_msg":"亲，你之前已经签过了","sign_time":1621787023249}],"page_no":4,"page_size":0,"pages":[5,6,7,8,9],"total_pages":9,"total":127,"first_page":3,"last_page":5},{"list":[{"name":"古风","avatar":"http://imgsrc.baidu.com/forum/pic/item/42a98226cffc1e178dac40694b90f603738de953.jpg","level_id":"14","cur_score":"19189","levelup_score":"30000","error_code":"160002","ret_msg":"亲，你之前已经签过了","sign_time":1621787023507},{"name":"opera","avatar":"http://imgsrc.baidu.com/forum/pic/item/7dd98d1001e939015be0433b7cec54e737d196d1.jpg","level_id":"14","cur_score":"19181","levelup_score":"30000","error_code":"160002","ret_msg":"亲，你之前已经签过了","sign_time":1621787023522},{"name":"成都驾校","avatar":"http://imgsrc.baidu.com/forum/pic/item/63d9f2d3572c11df2abc2efa622762d0f603c2fe.jpg","level_id":"14","cur_score":"18301","levelup_score":"30000","error_code":"160002","ret_msg":"亲，你之前已经签过了","sign_time":1621787023794},{"name":"成都学车","avatar":"http://tiebapic.baidu.com/forum/pic/item/902397dda144ad3420b96fe8c7a20cf431ad855f.jpg","level_id":"14","cur_score":"18624","levelup_score":"30000","error_code":"160002","ret_msg":"亲，你之前已经签过了","sign_time":1621787023799},{"name":"光环手游","avatar":"http://imgsrc.baidu.com/forum/pic/item/b999a9014c086e06fbd03b840a087bf40bd1cb81.jpg","level_id":"14","cur_score":"18276","levelup_score":"30000","error_code":"160002","ret_msg":"亲，你之前已经签过了","sign_time":1621787024066},{"name":"成鑫徐师","avatar":"http://imgsrc.baidu.com/forum/pic/item/4bed2e738bd4b31c453eecd784d6277f9e2ff858.jpg","level_id":"14","cur_score":"18237","levelup_score":"30000","error_code":"160002","ret_msg":"亲，你之前已经签过了","sign_time":1621787024318},{"name":"全民奇迹","avatar":"http://imgsrc.baidu.com/forum/pic/item/2f1422315c6034a8970ffb28c113495408237658.jpg","level_id":"14","cur_score":"18254","levelup_score":"30000","error_code":"160002","ret_msg":"亲，你之前已经签过了","sign_time":1621787024321},{"name":"模拟经营","avatar":"http://imgsrc.baidu.com/forum/pic/item/e61190ef76c6a7ef71685657fffaaf51f3de6671.jpg","level_id":"13","cur_score":"17905","levelup_score":"18000","error_code":"160002","ret_msg":"亲，你之前已经签过了","sign_time":1621787024510},{"name":"灵异","avatar":"http://imgsrc.baidu.com/forum/pic/item/9922720e0cf3d7ca3603f89cf01fbe096a63a967.jpg","level_id":"14","cur_score":"18122","levelup_score":"30000","error_code":"160002","ret_msg":"亲，你之前已经签过了","sign_time":1621787024442},{"name":"fedora","avatar":"http://imgsrc.baidu.com/forum/pic/item/f703738da97739124bd0bd5afb198618367ae213.jpg","level_id":"13","cur_score":"17899","levelup_score":"18000","error_code":"160002","ret_msg":"亲，你之前已经签过了","sign_time":1621787024663},{"name":"网金","avatar":"http://imgsrc.baidu.com/forum/pic/item/faf2b2119313b07e587ab6aa0dd7912396dd8c49.jpg","level_id":"13","cur_score":"17634","levelup_score":"18000","error_code":"160002","ret_msg":"亲，你之前已经签过了","sign_time":1621787024915},{"name":"world_of_dungeons","avatar":"http://imgsrc.baidu.com/forum/pic/item/d8f9d72a6059252ddd126faa359b033b5bb5b912.jpg","level_id":"13","cur_score":"16989","levelup_score":"18000","error_code":"160002","ret_msg":"亲，你之前已经签过了","sign_time":1621787025178},{"name":"暖暖环游世界","avatar":"http://imgsrc.baidu.com/forum/pic/item/aa18972bd40735fab618f7ce98510fb30e2408d8.jpg","level_id":"13","cur_score":"17581","levelup_score":"18000","error_code":"160002","ret_msg":"亲，你之前已经签过了","sign_time":1621787024921},{"name":"诛仙世界","avatar":"http://imgsrc.baidu.com/forum/pic/item/5266d0160924ab18d6754eba30fae6cd7a890bdf.jpg","level_id":"13","cur_score":"16618","levelup_score":"18000","error_code":"160002","ret_msg":"亲，你之前已经签过了","sign_time":1621787025266},{"name":"剑三交易","avatar":"http://imgsrc.baidu.com/forum/pic/item/10dfa9ec8a1363277a0bf8a9958fa0ec09fac741.jpg","level_id":"13","cur_score":"16321","levelup_score":"18000","error_code":"160002","ret_msg":"亲，你之前已经签过了","sign_time":1621787025433}],"page_no":5,"page_size":0,"pages":[5,6,7,8,9],"total_pages":9,"total":127,"first_page":4,"last_page":6},{"list":[{"name":"君威","avatar":"http://imgsrc.baidu.com/forum/pic/item/4034970a304e251fb0b958e3ae86c9177f3e535a.jpg","level_id":"13","cur_score":"16134","levelup_score":"18000","error_code":"160002","ret_msg":"亲，你之前已经签过了","sign_time":1621787025542},{"name":"smart","avatar":"http://tiebapic.baidu.com/forum/wh=120,120/sign=d51eb295f1cd7b89e93932823d146e96/35a85edf8db1cb13484d8e4cca54564e92584b4c.jpg","level_id":"13","cur_score":"16128","levelup_score":"18000","error_code":"160002","ret_msg":"亲，你之前已经签过了","sign_time":1621787025808},{"name":"mud","avatar":"http://imgsrc.baidu.com/forum/pic/item/6609c93d70cf3bc7d85f88b0d800baa1cd112a0a.jpg","level_id":"13","cur_score":"15820","levelup_score":"18000","error_code":"160002","ret_msg":"亲，你之前已经签过了","sign_time":1621787025855},{"name":"rime","avatar":"http://tiebapic.baidu.com/forum/pic/item/77c6a7efce1b9d16b473811de4deb48f8c546411.jpg","level_id":"13","cur_score":"15788","levelup_score":"18000","error_code":"160002","ret_msg":"亲，你之前已经签过了","sign_time":1621787025936},{"name":"ubuntu","avatar":"http://imgsrc.baidu.com/forum/pic/item/e7cd7b899e510fb3d06c4784db33c895d1430caf.jpg","level_id":"13","cur_score":"15688","levelup_score":"18000","error_code":"160002","ret_msg":"亲，你之前已经签过了","sign_time":1621787026026},{"name":"linuxmint","avatar":"http://imgsrc.baidu.com/forum/pic/item/8ad4b31c8701a18b46fc75aa9f2f07082938fec4.jpg","level_id":"13","cur_score":"15686","levelup_score":"18000","error_code":"160002","ret_msg":"亲，你之前已经签过了","sign_time":1621787026202},{"name":"totalcommander","avatar":"http://imgsrc.baidu.com/forum/pic/item/94cad1c8a786c91769cdc49acb3d70cf3ac75742.jpg","level_id":"13","cur_score":"15619","levelup_score":"18000","error_code":"160002","ret_msg":"亲，你之前已经签过了","sign_time":1621787026417},{"name":"civcrafter","avatar":"http://imgsrc.baidu.com/forum/pic/item/826f3b10b912c8fcacd52597f5039245d78821af.jpg","level_id":"13","cur_score":"15600","levelup_score":"18000","error_code":"160002","ret_msg":"亲，你之前已经签过了","sign_time":1621787026467},{"name":"金庸群侠传","avatar":"http://imgsrc.baidu.com/forum/pic/item/29381f30e924b8993fe1c8ff6c061d950b7bf61c.jpg","level_id":"13","cur_score":"15465","levelup_score":"18000","error_code":"160002","ret_msg":"亲，你之前已经签过了","sign_time":1621787026555},{"name":"战舰世界","avatar":"http://imgsrc.baidu.com/forum/pic/item/242dd42a2834349b13986607ceea15ce37d3be91.jpg","level_id":"13","cur_score":"15363","levelup_score":"18000","error_code":"160002","ret_msg":"亲，你之前已经签过了","sign_time":1621787026764},{"name":"大话西游2手游","avatar":"http://imgsrc.baidu.com/forum/pic/item/0d338744ebf81a4c209e0d33d02a6059242da698.jpg","level_id":"13","cur_score":"15362","levelup_score":"18000","error_code":"160002","ret_msg":"亲，你之前已经签过了","sign_time":1621787026850},{"name":"facerig","avatar":"http://imgsrc.baidu.com/forum/pic/item/d009b3de9c82d158699499518e0a19d8bc3e4238.jpg","level_id":"13","cur_score":"15336","levelup_score":"18000","error_code":"160002","ret_msg":"亲，你之前已经签过了","sign_time":1621787027115},{"name":"openwrt","avatar":"http://imgsrc.baidu.com/forum/pic/item/4a36acaf2edda3ccc9e64cac03e93901213f9238.jpg","level_id":"13","cur_score":"15319","levelup_score":"18000","error_code":"160002","ret_msg":"亲，你之前已经签过了","sign_time":1621787027159},{"name":"战舰世界亚服","avatar":"http://tiebapic.baidu.com/forum/pic/item/b3fb43166d224f4af38d09751ef790529822d144.jpg","level_id":"13","cur_score":"15332","levelup_score":"18000","error_code":"160002","ret_msg":"亲，你之前已经签过了","sign_time":1621787027184},{"name":"骑士精神","avatar":"http://imgsrc.baidu.com/forum/pic/item/3bf33a87e950352a68bfbe355043fbf2b2118b35.jpg","level_id":"13","cur_score":"14097","levelup_score":"18000","error_code":"160002","ret_msg":"亲，你之前已经签过了","sign_time":1621787027390}],"page_no":6,"page_size":0,"pages":[5,6,7,8,9],"total_pages":9,"total":127,"first_page":5,"last_page":7},{"list":[{"name":"wordpress","avatar":"http://imgsrc.baidu.com/forum/pic/item/574e9258d109b3de6f2b6172cfbf6c81800a4c10.jpg","level_id":"13","cur_score":"13993","levelup_score":"18000","error_code":"160002","ret_msg":"亲，你之前已经签过了","sign_time":1621787027473},{"name":"显卡","avatar":"http://imgsrc.baidu.com/forum/pic/item/7e3e6709c93d70cf4900d35af9dcd100bba12bea.jpg","level_id":"13","cur_score":"13972","levelup_score":"18000","error_code":"160002","ret_msg":"亲，你之前已经签过了","sign_time":1621787027722},{"name":"三国","avatar":"http://imgsrc.baidu.com/forum/pic/item/6b600c338744ebf8766e8e33d8f9d72a6059a79b.jpg","level_id":"13","cur_score":"13880","levelup_score":"18000","error_code":"160002","ret_msg":"亲，你之前已经签过了","sign_time":1621787027778},{"name":"cpu","avatar":"http://imgsrc.baidu.com/forum/pic/item/21a4462309f79052e4b8cdf00ef3d7ca7acbd55d.jpg","level_id":"13","cur_score":"13873","levelup_score":"18000","error_code":"160002","ret_msg":"亲，你之前已经签过了","sign_time":1621787027803},{"name":"图拉丁","avatar":"http://imgsrc.baidu.com/forum/pic/item/ac6eddc451da81cb02a12b515366d016082431e2.jpg","level_id":"13","cur_score":"13832","levelup_score":"18000","error_code":"160002","ret_msg":"亲，你之前已经签过了","sign_time":1621787028071},{"name":"steam","avatar":"https://imgsa.baidu.com/forum/pic/item/4f6bd333c895d143c24c8b1b7ff082025aaf071f.jpg","level_id":"13","cur_score":"13868","levelup_score":"18000","error_code":"160002","ret_msg":"亲，你之前已经签过了","sign_time":1621787028058},{"name":"rimworld","avatar":"http://imgsrc.baidu.com/forum/pic/item/34fae6cd7b899e51b4bb110c4ea7d933c8950df4.jpg","level_id":"13","cur_score":"13518","levelup_score":"18000","error_code":"160002","ret_msg":"亲，你之前已经签过了","sign_time":1621787028364},{"name":"显示器","avatar":"http://imgsrc.baidu.com/forum/pic/item/9e3df8dcd100baa11d0e811f4610b912c8fc2e70.jpg","level_id":"13","cur_score":"13301","levelup_score":"18000","error_code":"160002","ret_msg":"亲，你之前已经签过了","sign_time":1621787028399},{"name":"主板","avatar":"http://imgsrc.baidu.com/forum/pic/item/fd039245d688d43fbde737e87f1ed21b0ef43b59.jpg","level_id":"13","cur_score":"13371","levelup_score":"18000","error_code":"160002","ret_msg":"亲，你之前已经签过了","sign_time":1621787028399},{"name":"皇室战争","avatar":"http://tiebapic.baidu.com/forum/wh=120,120/sign=c69a01437759252da342150506ab2f0a/b21bb051f819861829190cdd5ded2e738bd4e609.jpg","level_id":"13","cur_score":"12321","levelup_score":"18000","error_code":"160002","ret_msg":"亲，你之前已经签过了","sign_time":1621787028735},{"name":"vmware","avatar":"http://imgsrc.baidu.com/forum/pic/item/a6efce1b9d16fdfa0c682edfbb8f8c5494ee7bff.jpg","level_id":"13","cur_score":"13299","levelup_score":"18000","error_code":"160002","ret_msg":"亲，你之前已经签过了","sign_time":1621787028736},{"name":"汉家松鼠","avatar":"http://imgsrc.baidu.com/forum/pic/item/faf2b2119313b07efa914eed07d7912397dd8c22.jpg","level_id":"13","cur_score":"11887","levelup_score":"18000","error_code":"160002","ret_msg":"亲，你之前已经签过了","sign_time":1621787028962},{"name":"固态硬盘","avatar":"http://imgsrc.baidu.com/forum/pic/item/aa64034f78f0f73619d240aa0255b319ebc41368.jpg","level_id":"13","cur_score":"11356","levelup_score":"18000","error_code":"160002","ret_msg":"亲，你之前已经签过了","sign_time":1621787029072},{"name":"htc","avatar":"http://imgsrc.baidu.com/forum/pic/item/d01373f082025aaf54dbbdaaf1edab64024f1ae2.jpg","level_id":"13","cur_score":"11297","levelup_score":"18000","error_code":"160002","ret_msg":"亲，你之前已经签过了","sign_time":1621787029116},{"name":"聚奎中学","avatar":"http://imgsrc.baidu.com/forum/pic/item/9922720e0cf3d7cab25d7dc4f31fbe096a63a9dd.jpg","level_id":"13","cur_score":"11240","levelup_score":"18000","error_code":"160002","ret_msg":"亲，你之前已经签过了","sign_time":1621787029345}],"page_no":7,"page_size":0,"pages":[5,6,7,8,9],"total_pages":9,"total":127,"first_page":6,"last_page":8},{"list":[{"name":"topgear","avatar":"http://imgsrc.baidu.com/forum/pic/item/18d8bc3eb13533fa90813db7aad3fd1f41345b77.jpg","level_id":"13","cur_score":"10865","levelup_score":"18000","error_code":"160002","ret_msg":"亲，你之前已经签过了","sign_time":1621787029415},{"name":"放置类游戏","avatar":"http://imgsrc.baidu.com/forum/pic/item/a2cc7cd98d1001e9e761bb30bb0e7bec54e797b4.jpg","level_id":"13","cur_score":"10343","levelup_score":"18000","error_code":"160002","ret_msg":"亲，你之前已经签过了","sign_time":1621787029632},{"name":"大天使之剑h5","avatar":"http://imgsrc.baidu.com/forum/pic/item/cefc1e178a82b9018ba5c2e17d8da9773812efdc.jpg","level_id":"13","cur_score":"10284","levelup_score":"18000","error_code":"160002","ret_msg":"亲，你之前已经签过了","sign_time":1621787029739},{"name":"放置江湖","avatar":"http://imgsrc.baidu.com/forum/pic/item/6a63f6246b600c337db5ac9e124c510fd8f9a19c.jpg","level_id":"13","cur_score":"10056","levelup_score":"18000","error_code":"160002","ret_msg":"亲，你之前已经签过了","sign_time":1621787029792},{"name":"掌心泥巴西游记","avatar":"http://imgsrc.baidu.com/forum/pic/item/960a304e251f95ca32d4696ece177f3e660952c1.jpg","level_id":"12","cur_score":"9998","levelup_score":"10000","error_code":"160002","ret_msg":"亲，你之前已经签过了","sign_time":1621787029961},{"name":"thinkpad","avatar":"http://imgsrc.baidu.com/forum/pic/item/58ee3d6d55fbb2fbfebb070a404a20a44623dc12.jpg","level_id":"12","cur_score":"8164","levelup_score":"10000","error_code":"160002","ret_msg":"亲，你之前已经签过了","sign_time":1621787030039},{"name":"不思议迷宫","avatar":"http://tiebapic.baidu.com/forum/pic/item/8326cffc1e178a82df0fcff5e103738da977e8b0.jpg","level_id":"12","cur_score":"7967","levelup_score":"10000","error_code":"160002","ret_msg":"亲，你之前已经签过了","sign_time":1621787030251},{"name":"kindle","avatar":"http://imgsrc.baidu.com/forum/pic/item/09fa513d269759ee66749f92bcfb43166d22df47.jpg","level_id":"12","cur_score":"7479","levelup_score":"10000","error_code":"160002","ret_msg":"亲，你之前已经签过了","sign_time":1621787030354},{"name":"eve","avatar":"http://imgsrc.baidu.com/forum/pic/item/c75c10385343fbf2055a3891b17eca8065388f0a.jpg","level_id":"12","cur_score":"7225","levelup_score":"10000","error_code":"160002","ret_msg":"亲，你之前已经签过了","sign_time":1621787030465},{"name":"野蛮人大作战","avatar":"http://tiebapic.baidu.com/forum/pic/item/faedab64034f78f08ce8cba56e310a55b2191c80.jpg","level_id":"12","cur_score":"7189","levelup_score":"10000","error_code":"160002","ret_msg":"亲，你之前已经签过了","sign_time":1621787030561},{"name":"完美世界","avatar":"http://imgsrc.baidu.com/forum/pic/item/1cda374e251f95ca3344909fc7177f3e660952b2.jpg","level_id":"12","cur_score":"7082","levelup_score":"10000","error_code":"160002","ret_msg":"亲，你之前已经签过了","sign_time":1621787030641},{"name":"温江","avatar":"http://imgsrc.baidu.com/forum/pic/item/472309f790529822b32977fad5ca7bcb0a46d4f5.jpg","level_id":"12","cur_score":"6416","levelup_score":"10000","error_code":"160002","ret_msg":"亲，你之前已经签过了","sign_time":1621787030856},{"name":"魔兽地图编辑器","avatar":"http://imgsrc.baidu.com/forum/pic/item/63d9f2d3572c11dfa849ac4c622762d0f603c2c0.jpg","level_id":"11","cur_score":"5434","levelup_score":"6000","error_code":"160002","ret_msg":"亲，你之前已经签过了","sign_time":1621787031012},{"name":"世界rpg","avatar":"http://imgsrc.baidu.com/forum/pic/item/5243fbf2b2119313653243ae62380cd791238dbf.jpg","level_id":"11","cur_score":"5415","levelup_score":"6000","error_code":"160002","ret_msg":"亲，你之前已经签过了","sign_time":1621787031078},{"name":"魔兽争霸","avatar":"http://imgsrc.baidu.com/forum/pic/item/fcfaaf51f3deb48faa23f17bf71f3a292cf578c8.jpg","level_id":"11","cur_score":"5313","levelup_score":"6000","error_code":"160002","ret_msg":"亲，你之前已经签过了","sign_time":1621787031163}],"page_no":8,"page_size":0,"pages":[5,6,7,8,9],"total_pages":9,"total":127,"first_page":7,"last_page":9},{"list":[{"name":"备孕","avatar":"https://tiebapic.baidu.com/forum/pic/item/b90e7bec54e736d19ad50c708c504fc2d4626980.jpg","level_id":"11","cur_score":"5184","levelup_score":"6000","error_code":"160002","ret_msg":"亲，你之前已经签过了","sign_time":1621787031262},{"name":"想不想修真","avatar":"http://tiebapic.baidu.com/forum/pic/item/3812b31bb051f8195e6d2a35cdb44aed2e73e701.jpg","level_id":"11","cur_score":"4825","levelup_score":"6000","error_code":"160002","ret_msg":"亲，你之前已经签过了","sign_time":1621787031454},{"name":"威联通","avatar":"http://imgsrc.baidu.com/forum/pic/item/472309f79052982272373c11d9ca7bcb0b46d4df.jpg","level_id":"10","cur_score":"2500","levelup_score":"3000","error_code":"160002","ret_msg":"亲，你之前已经签过了","sign_time":1621787031719},{"name":"环世界","avatar":"http://imgsrc.baidu.com/forum/pic/item/377adab44aed2e73f5b53c1c8401a18b87d6faa6.jpg","level_id":"11","cur_score":"4695","levelup_score":"6000","error_code":"340011","ret_msg":"你签得太快了，先看看贴子再来签吧:)","sign_time":1621787031692},{"name":"神武4","avatar":"http://tiebapic.baidu.com/forum/pic/item/a50f4bfbfbedab644b87edb9e036afc378311ed5.jpg","level_id":"10","cur_score":"2480","levelup_score":"3000","error_code":"160002","ret_msg":"亲，你之前已经签过了","sign_time":1621787031804},{"name":"至强","avatar":"http://tiebapic.baidu.com/forum/wh=120,120/sign=2173e3e4ae014a90816b4ebc9b471523/7e3e6709c93d70cf04a3f65befdcd100baa12b0e.jpg","level_id":"7","cur_score":"263","levelup_score":"500","error_code":"160002","ret_msg":"亲，你之前已经签过了","sign_time":1621787032109},{"name":"我的勇者游戏","avatar":"http://imgsrc.baidu.com/forum/pic/item/cf1b9d16fdfaaf51aaba9d78825494eef11f7a9f.jpg","level_id":"10","cur_score":"2351","levelup_score":"3000","error_code":"160002","ret_msg":"亲，你之前已经签过了","sign_time":1621787032239}],"page_no":9,"page_size":0,"pages":[5,6,7,8,9],"total_pages":9,"total":127,"first_page":8,"last_page":9}]}],"tuc":3,"ttc":134,"tsc":134,"tvc":1,"tbec":0,"tsuc":3}